livekit_memory/__init__.py
livekit_memory/__main__.py
livekit_memory/_version.py
livekit_memory/chunker/__init__.py
livekit_memory/chunker/agentic/__init__.py
livekit_memory/chunker/agentic/chunker.py
livekit_memory/chunker/agentic/prompts.py
livekit_memory/chunker/recursive/__init__.py
livekit_memory/chunker/recursive/chunker.py
livekit_memory/content/__init__.py
livekit_memory/content/loaders.py
livekit_memory/content/propositions.py
livekit_memory/content/types.py
livekit_memory/memory.py
livekit_memory/models.py
livekit_memory-0.2.5.dist-info/METADATA
livekit_memory-0.2.5.dist-info/WHEEL
livekit_memory-0.2.5.dist-info/entry_points.txt
livekit_memory-0.2.5.dist-info/RECORD
