Metadata-Version: 2.4
Name: livekit-memory
Version: 0.2.5
Summary: Memory - Document ingestion engine. Chunks and indexes knowledge sources into Qdrant to power LiveKit agent's contextual retrieval.
License: Apache-2.0
Keywords: livekit,rag,memory,qdrant,embeddings,retrieval
Author: joshiayush
Requires-Python: >=3.13,<4
Classifier: Development Status :: 3 - Alpha
Classifier: Intended Audience :: Developers
Classifier: License :: OSI Approved :: Apache Software License
Classifier: Programming Language :: Python :: 3
Classifier: Programming Language :: Python :: 3.13
Classifier: Topic :: Scientific/Engineering :: Artificial Intelligence
Requires-Dist: fastembed (>=0.7.4,<0.8.0)
Requires-Dist: httpx (>=0.27.0,<1.0.0)
Requires-Dist: langchain (>=1.1.2,<2.0.0)
Requires-Dist: langchain-core (>=1.1.1,<2.0.0)
Requires-Dist: langchain-google-vertexai (>=3.1.1,<4.0.0)
Requires-Dist: langchain-text-splitters (>=0.3.0,<1.0.0)
Requires-Dist: nltk (>=3.9.0,<4.0.0)
Requires-Dist: pypdf (>=5.1.0,<6.0.0)
Requires-Dist: qdrant-client (>=1.16.1,<2.0.0)
Requires-Dist: tidylog (>=0.1.1,<0.2.0)
Project-URL: Homepage, https://github.com/joshiayush/memory
Project-URL: Issues, https://github.com/joshiayush/memory/issues
Project-URL: Repository, https://github.com/joshiayush/memory
